rda_python_miscs/__init__.py
rda_python_miscs/bash_qsub.py
rda_python_miscs/bashqsub.py
rda_python_miscs/bashqsub.usg
rda_python_miscs/gdex_ls.py
rda_python_miscs/gdexls.py
rda_python_miscs/gdexls.usg
rda_python_miscs/gdexls_standalone.py
rda_python_miscs/pg_wget.py
rda_python_miscs/pgwget.py
rda_python_miscs/rda_cp.py
rda_python_miscs/rda_kill.py
rda_python_miscs/rda_mod.py
rda_python_miscs/rda_own.py
rda_python_miscs/rda_ps.py
rda_python_miscs/rda_sub.py
rda_python_miscs/rda_zip.py
rda_python_miscs/rdacp.py
rda_python_miscs/rdacp.usg
rda_python_miscs/rdakill.py
rda_python_miscs/rdakill.usg
rda_python_miscs/rdals.py
rda_python_miscs/rdals.usg
rda_python_miscs/rdamod.py
rda_python_miscs/rdamod.usg
rda_python_miscs/rdaown.py
rda_python_miscs/rdaown.usg
rda_python_miscs/rdaps.py
rda_python_miscs/rdaps.usg
rda_python_miscs/rdasub.py
rda_python_miscs/rdasub.usg
rda_python_miscs/rdazip.py
rda_python_miscs/rdazip.usg
rda_python_miscs/tcsh_qsub.py
rda_python_miscs/tcshqsub.py
rda_python_miscs/tcshqsub.usg
rda_python_miscs-2.0.1.dist-info/licenses/LICENSE
rda_python_miscs-2.0.1.dist-info/METADATA
rda_python_miscs-2.0.1.dist-info/WHEEL
rda_python_miscs-2.0.1.dist-info/entry_points.txt
rda_python_miscs-2.0.1.dist-info/top_level.txt
rda_python_miscs-2.0.1.dist-info/RECORD
